TrafficLight.vhd
LIBRARY IEEE;
USE IEEE.std_logic_1164.ALL;
USE IEEE.numeric_std.ALL;

ENTITY traffic_light IS
	PORT (clk: IN std_logic;
		  reset: IN std_logic;
		  idle_mode: IN std_logic;
		  TL1_g: OUT std_logic; --first traffic light green
		  TL1_y: OUT std_logic; --first traffic light yellow
		  TL1_r: OUT std_logic; --first traffic light red
		  TL2_g: OUT std_logic; --second traffic light green
		  TL2_y: OUT std_logic; --second traffic light yellow
		  TL2_r: OUT std_logic); --second traffic light red
END traffic_light;

ARCHITECTURE behavior OF traffic_light IS
	TYPE tl_state IS (first_g, first_y, second_g, second_y, all_red, idle); --check the status of the 2 traffic lights (green or yellow)
	SIGNAL previous_state, current_state, next_state: tl_state;
	SIGNAL timer: integer := 0;
	SIGNAL idle_blinker_counter: integer:= 0;
BEGIN
	state_sequence: PROCESS(clk, reset) --states order and timer settings
	BEGIN
	
		IF (reset = '1') THEN
			current_state <= first_g;
			timer <= 0;
		ELSE
			IF rising_edge(clk) THEN
				IF timer = 0 THEN
					previous_state <= current_state;
					current_state <= next_state;
					CASE next_state IS --timer duration
						WHEN first_g => timer <= 20;
						WHEN first_y => timer <= 6;
						WHEN second_g => timer <= 20;
						WHEN second_y => timer <= 6;
						WHEN all_red => timer <= 3;
						WHEN idle => timer <= 0;
					END CASE;
				ELSE
					timer <= timer - 1;
				END IF;
			END IF;
		END IF;
		
	END PROCESS;
	
	idle_blinker: PROCESS(clk, reset)
	BEGIN
	
		IF reset = '1' THEN
			idle_blinker_counter <= 0;
		ELSIF rising_edge(clk) THEN
			IF idle_mode = '1' THEN
				idle_blinker_counter <= idle_blinker_counter + 1;
				IF idle_blinker_counter >= 20 THEN
					idle_blinker_counter <= 0;
				END IF;
			ELSE
				idle_blinker_counter <= 0;
			END IF;
		END IF;
		
	END PROCESS;


	state_trasition: PROCESS(current_state) 
	BEGIN
	
		CASE current_state IS
			WHEN first_g => next_state <= first_y;
			WHEN first_y => next_state <= all_red;
			WHEN all_red =>
				IF previous_state = first_y THEN
					next_state <= second_g;
				ELSIF previous_state = second_y THEN
					next_state <= first_g;
				END IF;
			WHEN second_g => next_state <= second_y;
			WHEN second_y => next_state <= all_red;
			WHEN idle => next_state <= idle;
		END CASE;
		
	END PROCESS;
	
	
	tl_output: PROCESS(current_state) 
	BEGIN
		--TL default: all off
		TL1_g <= '0'; TL1_y <= '0'; TL1_r <= '0';
		TL2_g <= '0'; TL2_y <= '0'; TL2_r <= '0';
				
		IF idle_mode = '1' THEN
			IF idle_blinker_counter < 10 THEN
				TL1_y <= '1';
				TL2_y <= '1';
			END IF;
		ELSE
			CASE current_state IS
				WHEN first_g => TL1_g <= '1'; TL2_r <= '1'; 
				WHEN first_y => TL1_y <= '1'; TL2_r <= '1';
				WHEN second_g => TL2_g <= '1'; TL1_r <= '1'; 
				WHEN second_y => TL2_y <= '1'; TL1_r <= '1';
				WHEN all_red => TL1_r <= '1'; TL2_r <= '1';
				WHEN idle => NULL;
			END CASE;
		END IF;
		
	END PROCESS;
	
	
END behavior;

traffic_light_TB.vhd
LIBRARY IEEE;
USE IEEE.std_logic_1164.ALL;
USE IEEE.numeric_std.ALL;

ENTITY traffic_light_TB IS
END traffic_light_TB;

ARCHITECTURE behavior OF traffic_light_TB IS

    COMPONENT traffic_light
        PORT (
            clk        : IN  std_logic;
            reset      : IN  std_logic;
            idle_mode  : IN  std_logic;
            TL1_g      : OUT std_logic;
            TL1_y      : OUT std_logic;
            TL1_r      : OUT std_logic;
            TL2_g      : OUT std_logic;
            TL2_y      : OUT std_logic;
            TL2_r      : OUT std_logic
        );
    END COMPONENT;

    SIGNAL clk        : std_logic := '0';
    SIGNAL reset      : std_logic := '0';
    SIGNAL idle_mode  : std_logic := '0';
    SIGNAL TL1_g      : std_logic;
    SIGNAL TL1_y      : std_logic;
    SIGNAL TL1_r      : std_logic;
    SIGNAL TL2_g      : std_logic;
    SIGNAL TL2_y      : std_logic;
    SIGNAL TL2_r      : std_logic;

BEGIN

    uut: traffic_light
        PORT MAP (
            clk        => clk,
            reset      => reset,
            idle_mode  => idle_mode,
            TL1_g      => TL1_g,
            TL1_y      => TL1_y,
            TL1_r      => TL1_r,
            TL2_g      => TL2_g,
            TL2_y      => TL2_y,
            TL2_r      => TL2_r
        );

    clk_process : PROCESS
    BEGIN
        WHILE NOW < 2 us LOOP
            clk <= '0';
            WAIT FOR 5 ns;
            clk <= '1';
            WAIT FOR 5 ns;
        END LOOP;
        WAIT;  
    END PROCESS;

    test_start: PROCESS
    BEGIN
        -- Reset
        reset <= '1';
        WAIT FOR 20 ns;
        reset <= '0';

        -- Normal Run
        WAIT FOR 1 us;

        -- Idle
        idle_mode <= '1';

        WAIT FOR 800 ns;

        WAIT;
    END PROCESS;

END behavior;

TL_wave.vcd
$date
  Wed Jul 16 11:58:11 2025
$end
$version
  GHDL v0
$end
$timescale
  1 fs
$end
$scope module standard $end
$upscope $end
$scope module std_logic_1164 $end
$upscope $end
$scope module numeric_std $end
$upscope $end
$scope module traffic_light_tb $end
$var reg 1 ! clk $end
$var reg 1 " reset $end
$var reg 1 # idle_mode $end
$var reg 1 $ tl1_g $end
$var reg 1 % tl1_y $end
$var reg 1 & tl1_r $end
$var reg 1 ' tl2_g $end
$var reg 1 ( tl2_y $end
$var reg 1 ) tl2_r $end
$scope module uut $end
$var reg 1 * clk $end
$var reg 1 + reset $end
$var reg 1 , idle_mode $end
$var reg 1 - tl1_g $end
$var reg 1 . tl1_y $end
$var reg 1 / tl1_r $end
$var reg 1 0 tl2_g $end
$var reg 1 1 tl2_y $end
$var reg 1 2 tl2_r $end
$comment previous_state is not handled $end
$comment current_state is not handled $end
$comment next_state is not handled $end
$var integer 32 3 timer $end
$var integer 32 4 idle_blinker_counter $end
$upscope $end
$upscope $end
$enddefinitions $end
#0
0!
1"
0#
1$
0%
0&
0'
0(
1)
0*
1+
0,
1-
0.
0/
00
01
12
b0 3
b0 4
#5000000
1!
1*
#10000000
0!
0*
#15000000
1!
1*
#20000000
0!
0"
0*
0+
#25000000
1!
0$
1%
1*
0-
1.
12
b110 3
#30000000
0!
0*
#35000000
1!
1*
b101 3
#40000000
0!
0*
#45000000
1!
1*
b100 3
#50000000
0!
0*
#55000000
1!
1*
b11 3
#60000000
0!
0*
#65000000
1!
1*
b10 3
#70000000
0!
0*
#75000000
1!
1*
b1 3
#80000000
0!
0*
#85000000
1!
1*
b0 3
#90000000
0!
0*
#95000000
1!
0%
1&
1*
0.
1/
12
b11 3
#100000000
0!
0*
#105000000
1!
1*
b10 3
#110000000
0!
0*
#115000000
1!
1*
b1 3
#120000000
0!
0*
#125000000
1!
1*
b0 3
#130000000
0!
0*
#135000000
1!
1'
0)
1*
1/
10
02
b10100 3
#140000000
0!
0*
#145000000
1!
1*
b10011 3
#150000000
0!
0*
#155000000
1!
1*
b10010 3
#160000000
0!
0*
#165000000
1!
1*
b10001 3
#170000000
0!
0*
#175000000
1!
1*
b10000 3
#180000000
0!
0*
#185000000
1!
1*
b1111 3
#190000000
0!
0*
#195000000
1!
1*
b1110 3
#200000000
0!
0*
#205000000
1!
1*
b1101 3
#210000000
0!
0*
#215000000
1!
1*
b1100 3
#220000000
0!
0*
#225000000
1!
1*
b1011 3
#230000000
0!
0*
#235000000
1!
1*
b1010 3
#240000000
0!
0*
#245000000
1!
1*
b1001 3
#250000000
0!
0*
#255000000
1!
1*
b1000 3
#260000000
0!
0*
#265000000
1!
1*
b111 3
#270000000
0!
0*
#275000000
1!
1*
b110 3
#280000000
0!
0*
#285000000
1!
1*
b101 3
#290000000
0!
0*
#295000000
1!
1*
b100 3
#300000000
0!
0*
#305000000
1!
1*
b11 3
#310000000
0!
0*
#315000000
1!
1*
b10 3
#320000000
0!
0*
#325000000
1!
1*
b1 3
#330000000
0!
0*
#335000000
1!
1*
b0 3
#340000000
0!
0*
#345000000
1!
0'
1(
1*
1/
00
11
b110 3
#350000000
0!
0*
#355000000
1!
1*
b101 3
#360000000
0!
0*
#365000000
1!
1*
b100 3
#370000000
0!
0*
#375000000
1!
1*
b11 3
#380000000
0!
0*
#385000000
1!
1*
b10 3
#390000000
0!
0*
#395000000
1!
1*
b1 3
#400000000
0!
0*
#405000000
1!
1*
b0 3
#410000000
0!
0*
#415000000
1!
0(
1)
1*
1/
01
12
b11 3
#420000000
0!
0*
#425000000
1!
1*
b10 3
#430000000
0!
0*
#435000000
1!
1*
b1 3
#440000000
0!
0*
#445000000
1!
1*
b0 3
#450000000
0!
0*
#455000000
1!
1$
0&
1*
1-
0/
12
b10100 3
#460000000
0!
0*
#465000000
1!
1*
b10011 3
#470000000
0!
0*
#475000000
1!
1*
b10010 3
#480000000
0!
0*
#485000000
1!
1*
b10001 3
#490000000
0!
0*
#495000000
1!
1*
b10000 3
#500000000
0!
0*
#505000000
1!
1*
b1111 3
#510000000
0!
0*
#515000000
1!
1*
b1110 3
#520000000
0!
0*
#525000000
1!
1*
b1101 3
#530000000
0!
0*
#535000000
1!
1*
b1100 3
#540000000
0!
0*
#545000000
1!
1*
b1011 3
#550000000
0!
0*
#555000000
1!
1*
b1010 3
#560000000
0!
0*
#565000000
1!
1*
b1001 3
#570000000
0!
0*
#575000000
1!
1*
b1000 3
#580000000
0!
0*
#585000000
1!
1*
b111 3
#590000000
0!
0*
#595000000
1!
1*
b110 3
#600000000
0!
0*
#605000000
1!
1*
b101 3
#610000000
0!
0*
#615000000
1!
1*
b100 3
#620000000
0!
0*
#625000000
1!
1*
b11 3
#630000000
0!
0*
#635000000
1!
1*
b10 3
#640000000
0!
0*
#645000000
1!
1*
b1 3
#650000000
0!
0*
#655000000
1!
1*
b0 3
#660000000
0!
0*
#665000000
1!
0$
1%
1*
0-
1.
12
b110 3
#670000000
0!
0*
#675000000
1!
1*
b101 3
#680000000
0!
0*
#685000000
1!
1*
b100 3
#690000000
0!
0*
#695000000
1!
1*
b11 3
#700000000
0!
0*
#705000000
1!
1*
b10 3
#710000000
0!
0*
#715000000
1!
1*
b1 3
#720000000
0!
0*
#725000000
1!
1*
b0 3
#730000000
0!
0*
#735000000
1!
0%
1&
1*
0.
1/
12
b11 3
#740000000
0!
0*
#745000000
1!
1*
b10 3
#750000000
0!
0*
#755000000
1!
1*
b1 3
#760000000
0!
0*
#765000000
1!
1*
b0 3
#770000000
0!
0*
#775000000
1!
1'
0)
1*
1/
10
02
b10100 3
#780000000
0!
0*
#785000000
1!
1*
b10011 3
#790000000
0!
0*
#795000000
1!
1*
b10010 3
#800000000
0!
0*
#805000000
1!
1*
b10001 3
#810000000
0!
0*
#815000000
1!
1*
b10000 3
#820000000
0!
0*
#825000000
1!
1*
b1111 3
#830000000
0!
0*
#835000000
1!
1*
b1110 3
#840000000
0!
0*
#845000000
1!
1*
b1101 3
#850000000
0!
0*
#855000000
1!
1*
b1100 3
#860000000
0!
0*
#865000000
1!
1*
b1011 3
#870000000
0!
0*
#875000000
1!
1*
b1010 3
#880000000
0!
0*
#885000000
1!
1*
b1001 3
#890000000
0!
0*
#895000000
1!
1*
b1000 3
#900000000
0!
0*
#905000000
1!
1*
b111 3
#910000000
0!
0*
#915000000
1!
1*
b110 3
#920000000
0!
0*
#925000000
1!
1*
b101 3
#930000000
0!
0*
#935000000
1!
1*
b100 3
#940000000
0!
0*
#945000000
1!
1*
b11 3
#950000000
0!
0*
#955000000
1!
1*
b10 3
#960000000
0!
0*
#965000000
1!
1*
b1 3
#970000000
0!
0*
#975000000
1!
1*
b0 3
#980000000
0!
0*
#985000000
1!
0'
1(
1*
1/
00
11
b110 3
#990000000
0!
0*
#995000000
1!
1*
b101 3
#1000000000
0!
0*
#1005000000
1!
1*
b100 3
#1010000000
0!
0*
#1015000000
1!
1*
b11 3
#1020000000
0!
1#
0*
1,
#1025000000
1!
1*
b10 3
b1 4
#1030000000
0!
0*
#1035000000
1!
1*
b1 3
b10 4
#1040000000
0!
0*
#1045000000
1!
1*
b0 3
b11 4
#1050000000
0!
0*
#1055000000
1!
1%
0&
1*
1.
0/
11
b11 3
b100 4
#1060000000
0!
0*
#1065000000
1!
1*
b10 3
b101 4
#1070000000
0!
0*
#1075000000
1!
1*
b1 3
b110 4
#1080000000
0!
0*
#1085000000
1!
1*
b0 3
b111 4
#1090000000
0!
0*
#1095000000
1!
1*
1.
11
b10100 3
b1000 4
#1100000000
0!
0*
#1105000000
1!
1*
b10011 3
b1001 4
#1110000000
0!
0*
#1115000000
1!
1*
b10010 3
b1010 4
#1120000000
0!
0*
#1125000000
1!
1*
b10001 3
b1011 4
#1130000000
0!
0*
#1135000000
1!
1*
b10000 3
b1100 4
#1140000000
0!
0*
#1145000000
1!
1*
b1111 3
b1101 4
#1150000000
0!
0*
#1155000000
1!
1*
b1110 3
b1110 4
#1160000000
0!
0*
#1165000000
1!
1*
b1101 3
b1111 4
#1170000000
0!
0*
#1175000000
1!
1*
b1100 3
b10000 4
#1180000000
0!
0*
#1185000000
1!
1*
b1011 3
b10001 4
#1190000000
0!
0*
#1195000000
1!
1*
b1010 3
b10010 4
#1200000000
0!
0*
#1205000000
1!
1*
b1001 3
b10011 4
#1210000000
0!
0*
#1215000000
1!
1*
b1000 3
b10100 4
#1220000000
0!
0*
#1225000000
1!
1*
b111 3
b0 4
#1230000000
0!
0*
#1235000000
1!
1*
b110 3
b1 4
#1240000000
0!
0*
#1245000000
1!
1*
b101 3
b10 4
#1250000000
0!
0*
#1255000000
1!
1*
b100 3
b11 4
#1260000000
0!
0*
#1265000000
1!
1*
b11 3
b100 4
#1270000000
0!
0*
#1275000000
1!
1*
b10 3
b101 4
#1280000000
0!
0*
#1285000000
1!
1*
b1 3
b110 4
#1290000000
0!
0*
#1295000000
1!
1*
b0 3
b111 4
#1300000000
0!
0*
#1305000000
1!
1*
1.
11
b110 3
b1000 4
#1310000000
0!
0*
#1315000000
1!
1*
b101 3
b1001 4
#1320000000
0!
0*
#1325000000
1!
1*
b100 3
b1010 4
#1330000000
0!
0*
#1335000000
1!
1*
b11 3
b1011 4
#1340000000
0!
0*
#1345000000
1!
1*
b10 3
b1100 4
#1350000000
0!
0*
#1355000000
1!
1*
b1 3
b1101 4
#1360000000
0!
0*
#1365000000
1!
1*
b0 3
b1110 4
#1370000000
0!
0*
#1375000000
1!
0%
0(
1*
0.
01
b11 3
b1111 4
#1380000000
0!
0*
#1385000000
1!
1*
b10 3
b10000 4
#1390000000
0!
0*
#1395000000
1!
1*
b1 3
b10001 4
#1400000000
0!
0*
#1405000000
1!
1*
b0 3
b10010 4
#1410000000
0!
0*
#1415000000
1!
1*
b10100 3
b10011 4
#1420000000
0!
0*
#1425000000
1!
1*
b10011 3
b10100 4
#1430000000
0!
0*
#1435000000
1!
1*
b10010 3
b0 4
#1440000000
0!
0*
#1445000000
1!
1*
b10001 3
b1 4
#1450000000
0!
0*
#1455000000
1!
1*
b10000 3
b10 4
#1460000000
0!
0*
#1465000000
1!
1*
b1111 3
b11 4
#1470000000
0!
0*
#1475000000
1!
1*
b1110 3
b100 4
#1480000000
0!
0*
#1485000000
1!
1*
b1101 3
b101 4
#1490000000
0!
0*
#1495000000
1!
1*
b1100 3
b110 4
#1500000000
0!
0*
#1505000000
1!
1*
b1011 3
b111 4
#1510000000
0!
0*
#1515000000
1!
1*
b1010 3
b1000 4
#1520000000
0!
0*
#1525000000
1!
1*
b1001 3
b1001 4
#1530000000
0!
0*
#1535000000
1!
1*
b1000 3
b1010 4
#1540000000
0!
0*
#1545000000
1!
1*
b111 3
b1011 4
#1550000000
0!
0*
#1555000000
1!
1*
b110 3
b1100 4
#1560000000
0!
0*
#1565000000
1!
1*
b101 3
b1101 4
#1570000000
0!
0*
#1575000000
1!
1*
b100 3
b1110 4
#1580000000
0!
0*
#1585000000
1!
1*
b11 3
b1111 4
#1590000000
0!
0*
#1595000000
1!
1*
b10 3
b10000 4
#1600000000
0!
0*
#1605000000
1!
1*
b1 3
b10001 4
#1610000000
0!
0*
#1615000000
1!
1*
b0 3
b10010 4
#1620000000
0!
0*
#1625000000
1!
1*
b110 3
b10011 4
#1630000000
0!
0*
#1635000000
1!
1*
b101 3
b10100 4
#1640000000
0!
0*
#1645000000
1!
1*
b100 3
b0 4
#1650000000
0!
0*
#1655000000
1!
1*
b11 3
b1 4
#1660000000
0!
0*
#1665000000
1!
1*
b10 3
b10 4
#1670000000
0!
0*
#1675000000
1!
1*
b1 3
b11 4
#1680000000
0!
0*
#1685000000
1!
1*
b0 3
b100 4
#1690000000
0!
0*
#1695000000
1!
1%
1(
1*
1.
11
b11 3
b101 4
#1700000000
0!
0*
#1705000000
1!
1*
b10 3
b110 4
#1710000000
0!
0*
#1715000000
1!
1*
b1 3
b111 4
#1720000000
0!
0*
#1725000000
1!
1*
b0 3
b1000 4
#1730000000
0!
0*
#1735000000
1!
1*
1.
11
b10100 3
b1001 4
#1740000000
0!
0*
#1745000000
1!
1*
b10011 3
b1010 4
#1750000000
0!
0*
#1755000000
1!
1*
b10010 3
b1011 4
#1760000000
0!
0*
#1765000000
1!
1*
b10001 3
b1100 4
#1770000000
0!
0*
#1775000000
1!
1*
b10000 3
b1101 4
#1780000000
0!
0*
#1785000000
1!
1*
b1111 3
b1110 4
#1790000000
0!
0*
#1795000000
1!
1*
b1110 3
b1111 4
#1800000000
0!
0*
#1805000000
1!
1*
b1101 3
b10000 4
#1810000000
0!
0*
#1815000000
1!
1*
b1100 3
b10001 4
#1820000000
0!
0*
#1825000000
1!
1*
b1011 3
b10010 4
#1830000000
0!
0*
#1835000000
1!
1*
b1010 3
b10011 4
#1840000000
0!
0*
#1845000000
1!
1*
b1001 3
b10100 4
#1850000000
0!
0*
#1855000000
1!
1*
b1000 3
b0 4
#1860000000
0!
0*
#1865000000
1!
1*
b111 3
b1 4
#1870000000
0!
0*
#1875000000
1!
1*
b110 3
b10 4
#1880000000
0!
0*
#1885000000
1!
1*
b101 3
b11 4
#1890000000
0!
0*
#1895000000
1!
1*
b100 3
b100 4
#1900000000
0!
0*
#1905000000
1!
1*
b11 3
b101 4
#1910000000
0!
0*
#1915000000
1!
1*
b10 3
b110 4
#1920000000
0!
0*
#1925000000
1!
1*
b1 3
b111 4
#1930000000
0!
0*
#1935000000
1!
1*
b0 3
b1000 4
#1940000000
0!
0*
#1945000000
1!
1*
1.
11
b110 3
b1001 4
#1950000000
0!
0*
#1955000000
1!
1*
b101 3
b1010 4
#1960000000
0!
0*
#1965000000
1!
1*
b100 3
b1011 4
#1970000000
0!
0*
#1975000000
1!
1*
b11 3
b1100 4
#1980000000
0!
0*
#1985000000
1!
1*
b10 3
b1101 4
#1990000000
0!
0*
#1995000000
1!
1*
b1 3
b1110 4
